main.py
pickaxe_mcp_semantic_scholar-0.1.5.dist-info/METADATA
pickaxe_mcp_semantic_scholar-0.1.5.dist-info/WHEEL
pickaxe_mcp_semantic_scholar-0.1.5.dist-info/entry_points.txt
pickaxe_mcp_semantic_scholar-0.1.5.dist-info/top_level.txt
pickaxe_mcp_semantic_scholar-0.1.5.dist-info/RECORD
